morl4water/__init__.py
morl4water/core/__init__.py
morl4water/core/envs/__init__.py
morl4water/core/envs/water_management_system.py
morl4water/core/models/__init__.py
morl4water/core/models/catchment.py
morl4water/core/models/facility.py
morl4water/core/models/flow.py
morl4water/core/models/irrigation_district.py
morl4water/core/models/objective.py
morl4water/core/models/power_plant.py
morl4water/core/models/reservoir.py
morl4water/core/models/reservoir_with_pump.py
morl4water/core/models/weir.py
morl4water/core/utils/__init__.py
morl4water/core/utils/utils.py
morl4water/core/wrappers/__init__.py
morl4water/core/wrappers/transform_action.py
morl4water/examples/__init__.py
morl4water/examples/nile_river_simulation.py
morl4water/examples/omo_river_simulation.py
morl4water/examples/susquehanna_river_simulation.py
morl4water/examples/data/__init__.py
morl4water/examples/data/nile_river/__init__.py
morl4water/examples/data/nile_river/catchments/InflowAtbara.txt
morl4water/examples/data/nile_river/catchments/InflowBlueNile.txt
morl4water/examples/data/nile_river/catchments/InflowDinder.txt
morl4water/examples/data/nile_river/catchments/InflowGERDToRoseires.txt
morl4water/examples/data/nile_river/catchments/InflowRahad.txt
morl4water/examples/data/nile_river/catchments/InflowRoseiresToAbuNaama.txt
morl4water/examples/data/nile_river/catchments/InflowSukiToSennar.txt
morl4water/examples/data/nile_river/catchments/InflowWhiteNile.txt
morl4water/examples/data/nile_river/catchments/__init__.py
morl4water/examples/data/nile_river/irrigation/__init__.py
morl4water/examples/data/nile_river/irrigation/irr_demand_DSSennar.txt
morl4water/examples/data/nile_river/irrigation/irr_demand_Egypt.txt
morl4water/examples/data/nile_river/irrigation/irr_demand_Gezira.txt
morl4water/examples/data/nile_river/irrigation/irr_demand_Hassanab.txt
morl4water/examples/data/nile_river/irrigation/irr_demand_Tamaniat.txt
morl4water/examples/data/nile_river/irrigation/irr_demand_USSennar.txt
morl4water-0.1.3.dist-info/licenses/LICENSE
morl4water-0.1.3.dist-info/METADATA
morl4water-0.1.3.dist-info/WHEEL
morl4water-0.1.3.dist-info/top_level.txt
morl4water-0.1.3.dist-info/RECORD
